./.dockerignore
./.env.template
./.gitignore
./.python-version
./Dockerfile
./PKG-INFO
./README.md
./client.py
./middleware.py
./pyproject.toml
./server.py
./settings.py
./uv.lock
./version.py
./.cursor/rules/mcp-guidelines.mdc
./.cursor/rules/project-structure.mdc
./.cursor/rules/python.mdc
./.cursor/rules/tool-development-guide.mdc
./docs/DEPLOYMENT.md
./docs/LOCAL_BUILD.md
./tools/__init__.py
./tools/assets.py
./tools/dsl.py
./tools/glossary.py
./tools/lineage.py
./tools/models.py
./tools/query.py
./tools/search.py
./utils/__init__.py
./utils/constants.py
./utils/parameters.py
./utils/search.py
atlan_mcp_server-0.2.12.dist-info/METADATA
atlan_mcp_server-0.2.12.dist-info/WHEEL
atlan_mcp_server-0.2.12.dist-info/entry_points.txt
atlan_mcp_server-0.2.12.dist-info/RECORD
