Metadata-Version: 2.4
Name: atlan-mcp-server
Version: 0.2.12
Summary: Atlan Model Context Protocol server for interacting with Atlan services
Project-URL: Homepage, https://github.com/atlanhq/agent-toolkit
Project-URL: Documentation, https://ask.atlan.com/hc/en-us/articles/12525731740175-How-to-implement-the-Atlan-MCP-server
Project-URL: Bug Tracker, https://github.com/atlanhq/agent-toolkit/issues
Project-URL: Source, https://github.com/atlanhq/agent-toolkit.git
Project-URL: Changelog, https://github.com/atlanhq/agent-toolkit/blob/main/CHANGELOG.md
Author-email: AtlanHQ <engineering@atlan.com>
License: MIT
Classifier: License :: OSI Approved :: MIT License
Classifier: Operating System :: OS Independent
Classifier: Programming Language :: Python :: 3
Classifier: Programming Language :: Python :: 3.11
Requires-Python: >=3.11
Requires-Dist: fastmcp==2.13.0.2
Requires-Dist: pyatlan>=6.0.1
Requires-Dist: uvicorn>=0.35.0
